{
   "ind" : {
      "service_ind" : "",
      "op_ind" : ""
    },
   "src_in_data" : {
      "isAvailable" : false,
      "file_nm" : "",
      "file_typ" : "",
      "file" : null
    },
    "trgt_in_data" : {
      "isAvailable" : false,
      "file_nm" : "",
      "file_typ" : "",
      "file" : null
    },
    "final_op_data" : {
      "isAvailable" : false,
      "file_nm" : "",
      "file_typ" : "",
      "file" : null
    },
    "aux_op_data" : {
      "isAvailable" : false,
      "file_nm" : "",
      "file_typ" : "",
      "file" : null
    },
  "msg" : {
    "msg_val" : "",
    "msg_cause": ""
  },
  "db" : {
    "db_nm" : "",
    "vec_dim": 0,
    "op_k": 0,
    "word_wt_ds": 0,
    "meta_wt_ds": 0,
    "threshold_ds": 0
  }

}
